stack_watcher/main.py
stack_watcher/__init__.py
stack_watcher/test/__init__.py
stack_watcher/test/test_main.py
stack_watcher/test/resources/feed.json
stack_watcher-0.3.4.dist-info/entry_points.txt
stack_watcher-0.3.4.dist-info/top_level.txt
stack_watcher-0.3.4.dist-info/METADATA
stack_watcher-0.3.4.dist-info/DESCRIPTION.rst
stack_watcher-0.3.4.dist-info/metadata.json
stack_watcher-0.3.4.dist-info/WHEEL
stack_watcher-0.3.4.dist-info/RECORD
