Metadata-Version: 2.0
Name: stack-watcher
Version: 0.3.4
Summary: Be the first to answer questions on Stack Exchange web sites with this library
Requires-Dist: requests (>=2.3.0)
Requires-Dist: docopt (>=0.6.1)
